PythonHeimofaShouce/README.md
PythonHeimofaShouce/__init__.py
PythonHeimofaShouce/__main__.py
PythonHeimofaShouce/file.epub
PythonHeimofaShouce/index.html
PythonHeimofaShouce/css/__init__.py
PythonHeimofaShouce/css/annotations.css
PythonHeimofaShouce/css/main.css
PythonHeimofaShouce/css/normalize.css
PythonHeimofaShouce/css/popup.css
PythonHeimofaShouce/font/__init__.py
PythonHeimofaShouce/font/fontello.eot
PythonHeimofaShouce/font/fontello.svg
PythonHeimofaShouce/font/fontello.ttf
PythonHeimofaShouce/font/fontello.woff
PythonHeimofaShouce/img/__init__.py
PythonHeimofaShouce/img/annotator-glyph-sprite.png
PythonHeimofaShouce/img/annotator-icon-sprite.png
PythonHeimofaShouce/img/apple-touch-icon.png
PythonHeimofaShouce/img/cancelfullscreen.png
PythonHeimofaShouce/img/close.png
PythonHeimofaShouce/img/fullscreen.png
PythonHeimofaShouce/img/loader.gif
PythonHeimofaShouce/img/menu-icon.png
PythonHeimofaShouce/img/save.png
PythonHeimofaShouce/img/saved.png
PythonHeimofaShouce/img/settings-s.png
PythonHeimofaShouce/img/settings.png
PythonHeimofaShouce/img/star.png
PythonHeimofaShouce/js/__init__.py
PythonHeimofaShouce/js/epub.js
PythonHeimofaShouce/js/epub.min.js
PythonHeimofaShouce/js/epub.min.map
PythonHeimofaShouce/js/hooks.min.js
PythonHeimofaShouce/js/hooks.min.map
PythonHeimofaShouce/js/reader.js
PythonHeimofaShouce/js/reader.js.map
PythonHeimofaShouce/js/reader.min.js
PythonHeimofaShouce/js/reader.min.map
PythonHeimofaShouce/js/hooks/__init__.py
PythonHeimofaShouce/js/hooks/extensions/__init__.py
PythonHeimofaShouce/js/hooks/extensions/highlight.js
PythonHeimofaShouce/js/libs/__init__.py
PythonHeimofaShouce/js/libs/jquery.min.js
PythonHeimofaShouce/js/libs/localforage.min.js
PythonHeimofaShouce/js/libs/screenfull.js
PythonHeimofaShouce/js/libs/screenfull.min.js
PythonHeimofaShouce/js/libs/zip.min.js
PythonHeimofaShouce/js/plugins/__init__.py
PythonHeimofaShouce/js/plugins/hypothesis.js
PythonHeimofaShouce/js/plugins/search.js
python_heimofa_shouce-2024.3.6.0.dist-info/METADATA
python_heimofa_shouce-2024.3.6.0.dist-info/WHEEL
python_heimofa_shouce-2024.3.6.0.dist-info/entry_points.txt
python_heimofa_shouce-2024.3.6.0.dist-info/top_level.txt
python_heimofa_shouce-2024.3.6.0.dist-info/RECORD
